reservoirflow/__init__.py
reservoirflow/__main__.py
reservoirflow/base.py
reservoirflow/backends/__init__.py
reservoirflow/backends/backend.py
reservoirflow/backends/jax.py
reservoirflow/backends/numpy.py
reservoirflow/backends/pytorch.py
reservoirflow/backends/tensorflow.py
reservoirflow/fluids/__init__.py
reservoirflow/fluids/fluid.py
reservoirflow/fluids/multi_phase.py
reservoirflow/fluids/single_phase.py
reservoirflow/fluids/three_phase.py
reservoirflow/fluids/two_phase.py
reservoirflow/grids/__init__.py
reservoirflow/grids/grid.py
reservoirflow/grids/irregular_cartesian.py
reservoirflow/grids/radial.py
reservoirflow/grids/regular_cartesian.py
reservoirflow/models/__init__.py
reservoirflow/models/black_oil.py
reservoirflow/models/compositional.py
reservoirflow/models/model.py
reservoirflow/models/thermal.py
reservoirflow/scalers/__init__.py
reservoirflow/scalers/dummy.py
reservoirflow/scalers/minmax.py
reservoirflow/scalers/scaler.py
reservoirflow/scalers/scalerdc.py
reservoirflow/solutions/__init__.py
reservoirflow/solutions/compiler.py
reservoirflow/solutions/solution.py
reservoirflow/solutions/analytical/__init__.py
reservoirflow/solutions/analytical/d1p1.py
reservoirflow/solutions/analytical/d1p2.py
reservoirflow/solutions/analytical/d1p3.py
reservoirflow/solutions/analytical/d2p1.py
reservoirflow/solutions/analytical/d2p2.py
reservoirflow/solutions/analytical/d2p3.py
reservoirflow/solutions/analytical/d3p1.py
reservoirflow/solutions/analytical/d3p2.py
reservoirflow/solutions/analytical/d3p3.py
reservoirflow/solutions/neurical/__init__.py
reservoirflow/solutions/neurical/deeponet.py
reservoirflow/solutions/neurical/pinn.py
reservoirflow/solutions/numerical/__init__.py
reservoirflow/solutions/numerical/fdm.py
reservoirflow/solutions/numerical/fem.py
reservoirflow/solutions/numerical/fvm.py
reservoirflow/solutions/numerical/solvers.py
reservoirflow/utils/__init__.py
reservoirflow/utils/helpers.py
reservoirflow/utils/profme.py
reservoirflow/utils/pyvista.py
reservoirflow-0.1.0b3.dist-info/LICENSE
reservoirflow-0.1.0b3.dist-info/METADATA
reservoirflow-0.1.0b3.dist-info/WHEEL
reservoirflow-0.1.0b3.dist-info/top_level.txt
reservoirflow-0.1.0b3.dist-info/RECORD
