Metadata-Version: 2.1
Name: reservoirflow
Version: 0.1.0b3
Summary: Reservoir Simulation and Engineering Library in Python
Author: Hiesab
Author-email: contact@hiesab.com
Maintainer: Zakariya Abugrin
Maintainer-email: zakariya.abugrin@hiesab.com
License: Creative Commons Attribution-NonCommercial-ShareAlike 4.0 International
Project-URL: Website, https://www.hiesab.com/en/products/reservoirflow/
Project-URL: GitHub, https://github.com/hiesabx/reservoirflow
Project-URL: Documentation, https://github.com/hiesabx/reservoirflow
Keywords: Petroleum,Reservoir,Simulation,Scientific Computing
Classifier: Development Status :: 4 - Beta
Classifier: Intended Audience :: Developers
Classifier: Intended Audience :: Education
Classifier: Programming Language :: Python :: 3.11
Classifier: Topic :: Scientific/Engineering
Classifier: Topic :: Scientific/Engineering :: Physics
Classifier: Topic :: Scientific/Engineering :: Visualization
Classifier: Topic :: Scientific/Engineering :: Artificial Intelligence
Requires-Python: >=3.8
License-File: LICENSE
Requires-Dist: line-profiler==4.2.0
Requires-Dist: matplotlib==3.10.0
Requires-Dist: numpy==2.1.0
Requires-Dist: pandas==2.2.2
Requires-Dist: scipy==1.13.1
Requires-Dist: sympy==1.13.1
Requires-Dist: tabulate==0.9.0
Requires-Dist: tqdm==4.67.1
Requires-Dist: pyvista==0.45.0
Requires-Dist: ipywidgets==8.1.6
Requires-Dist: aiohttp==3.11.11
Requires-Dist: trame==3.9.0
